logfmt1/__init__.py
logfmt1/logex.py
logfmt1/logfmt1.py
logfmt1/update_logfmt.py
logfmt1/update_logfmt_all.py
logfmt1/share/apache.clf.fmt
logfmt1/share/apache.combined.fmt
logfmt1/share/apache.error.fmt
logfmt1/share/apache.fmt
logfmt1/share/grok.fmt
logfmt1/share/inilog.fmt
logfmt1/share/nginx.fmt
logfmt1/share/strftime.fmt
logfmt1/share/update/apache
logfmt1/share/update/nginx
logfmt1-0.5.3.dist-info/METADATA
logfmt1-0.5.3.dist-info/WHEEL
logfmt1-0.5.3.dist-info/entry_points.txt
logfmt1-0.5.3.dist-info/top_level.txt
logfmt1-0.5.3.dist-info/RECORD
