Metadata-Version: 2.1
Name: logfmt1
Version: 0.5.3
Summary: handle *.log.fmt specifiers and regex conversion
Home-page: https://fossil.include-once.org/modseccfg/wiki/logfmt1
License: Apache-2.0
Project-URL: Documentation, https://fossil.include-once.org/modseccfg/doc/trunk//logfmt1/html/index.html
Keywords: io
Platform: UNKNOWN
Classifier: Topic :: Software Development :: Libraries :: Python Modules
Requires-Python: >= 3.6
